rython_calc-0.5.3.dist-info/METADATA
rython_calc-0.5.3.dist-info/WHEEL
rython_calc-0.5.3.dist-info/licenses/LICENSE
rython/py.typed
rython/rython_calc.pyi
rython/__init__.py
rython/rython_calc.cp312-win32.pyd
rython_calc-0.5.3.dist-info/RECORD
