Metadata-Version: 2.3
Name: rython_calc
Version: 0.5.3
Classifier: Development Status :: 1 - Planning
Classifier: Programming Language :: Rust
Classifier: Programming Language :: Python :: Implementation :: CPython
Classifier: Programming Language :: Python :: Implementation :: PyPy
License-File: LICENSE
Summary: Small project developed by me to learn PyO3 library.
Author-email: Krystian Krakowski <kkrakowski22@gmail.com>
Maintainer-email: Krystian Krakowski <kkrakowski22@gmail.com>
Requires-Python: >=3.12
Project-URL: Homepage, https://github.com/fawq/Rython
Project-URL: Source, https://github.com/fawq/Rython
